measure.py
measurer-1.0.0.dist-info/LICENSE
measurer-1.0.0.dist-info/METADATA
measurer-1.0.0.dist-info/WHEEL
measurer-1.0.0.dist-info/top_level.txt
measurer-1.0.0.dist-info/RECORD
