Metadata-Version: 2.1
Name: measurer
Version: 1.0.0
Summary: Easily measure Python function performance
Home-page: https://github.com/sharrik111/measurer
Author: sharrik111
Author-email: sharrik111@gmail.com
License: Unlicense
Platform: UNKNOWN
Classifier: Programming Language :: Python :: 3
Classifier: Development Status :: 5 - Production/Stable
Classifier: License :: OSI Approved :: The Unlicense (Unlicense)
Classifier: Operating System :: OS Independent
Requires-Python: >=3.6
License-File: LICENSE
